lintang/__init__.py
lintang/calc.py
lintang/calendar.py
lintang/core.py
lintang-0.0.5.dist-info/METADATA
lintang-0.0.5.dist-info/WHEEL
lintang-0.0.5.dist-info/top_level.txt
lintang-0.0.5.dist-info/RECORD
