Metadata-Version: 2.1
Name: lintang
Version: 0.0.5
Summary: Lintang
Home-page: https://gitlab.com/liokta/arrya
Author: Liokta Bagaskara
Author-email: shiroasasin@gmail.com
License: UNKNOWN
Platform: UNKNOWN
Classifier: Programming Language :: Python :: 3
Classifier: License :: OSI Approved :: MIT License
Classifier: Operating System :: OS Independent
